<streamingInfos>
		<item>	
			<title>"[COLOR red][B]Powered by e-doctor[/B][/COLOR]"</title>
			<link>plugin://plugin.video.youtube/?path=/root/video&action=play_video&videoid=GA0N0Bu5JiE</link>
		<item>
			<title>"[COLOR red][B]http://e-doctor.webstarts.com[/B][/COLOR]"</title>
			<link>plugin://plugin.video.youtube/?path=/root/video&action=play_video&videoid=GA0N0Bu5JiE</link>






		<item>
			<title>DK: DK4</title>
			<link>plugin://plugin.video.f4mTester/?streamtype=TSDOWNLOADER&amp;name=Powered_By_e-Doctor_e-Modder;url=http://ksportiptv.com:1557/live/enigma10/VUNuVnnJhQ/3295.ts</link>
		
		<item>
			<title>DK: DK1</title>
			<link>plugin://plugin.video.f4mTester/?streamtype=TSDOWNLOADER&amp;name=Powered_By_e-Doctor_e-Modder;url=http://ksportiptv.com:1557/live/enigma10/VUNuVnnJhQ/3296.ts</link>
		
		<item>
			<title>DK: Disney Channel</title>
			<link>plugin://plugin.video.f4mTester/?streamtype=TSDOWNLOADER&amp;name=Powered_By_e-Doctor_e-Modder;url=http://ksportiptv.com:1557/live/enigma10/VUNuVnnJhQ/3331.ts</link>
		
		<item>
			<title>DK: Dicovery Channel HD</title>
			<link>plugin://plugin.video.f4mTester/?streamtype=TSDOWNLOADER&amp;name=Powered_By_e-Doctor_e-Modder;url=http://ksportiptv.com:1557/live/enigma10/VUNuVnnJhQ/3332.ts</link>
		
		<item>
			<title>DK: Carton Network</title>
			<link>plugin://plugin.video.f4mTester/?streamtype=TSDOWNLOADER&amp;name=Powered_By_e-Doctor_e-Modder;url=http://ksportiptv.com:1557/live/enigma10/VUNuVnnJhQ/3333.ts</link>
		
		<item>
			<title>DK: C More Sport</title>
			<link>plugin://plugin.video.f4mTester/?streamtype=TSDOWNLOADER&amp;name=Powered_By_e-Doctor_e-Modder;url=http://ksportiptv.com:1557/live/enigma10/VUNuVnnJhQ/3334.ts</link>
		
		<item>
			<title>DK: VIASAT SPORT</title>
			<link>plugin://plugin.video.f4mTester/?streamtype=TSDOWNLOADER&amp;name=Powered_By_e-Doctor_e-Modder;url=http://ksportiptv.com:1557/live/enigma10/VUNuVnnJhQ/3298.ts</link>
		
		<item>
			<title>DK: VIASAT SERIES</title>
			<link>plugin://plugin.video.f4mTester/?streamtype=TSDOWNLOADER&amp;name=Powered_By_e-Doctor_e-Modder;url=http://ksportiptv.com:1557/live/enigma10/VUNuVnnJhQ/3299.ts</link>
		
		<item>
			<title>DK: VIASAT NATURE</title>
			<link>plugin://plugin.video.f4mTester/?streamtype=TSDOWNLOADER&amp;name=Powered_By_e-Doctor_e-Modder;url=http://ksportiptv.com:1557/live/enigma10/VUNuVnnJhQ/3300.ts</link>
		
		<item>
			<title>DK: VIASAT MOTOR</title>
			<link>plugin://plugin.video.f4mTester/?streamtype=TSDOWNLOADER&amp;name=Powered_By_e-Doctor_e-Modder;url=http://ksportiptv.com:1557/live/enigma10/VUNuVnnJhQ/3301.ts</link>
		
		<item>
			<title>DK: VIASAT HISTORY</title>
			<link>plugin://plugin.video.f4mTester/?streamtype=TSDOWNLOADER&amp;name=Powered_By_e-Doctor_e-Modder;url=http://ksportiptv.com:1557/live/enigma10/VUNuVnnJhQ/3302.ts</link>
		
		<item>
			<title>DK: VIASAT GOLF</title>
			<link>plugin://plugin.video.f4mTester/?streamtype=TSDOWNLOADER&amp;name=Powered_By_e-Doctor_e-Modder;url=http://ksportiptv.com:1557/live/enigma10/VUNuVnnJhQ/3303.ts</link>
		
		<item>
			<title>DK: VIASAT FOTBOOLL</title>
			<link>plugin://plugin.video.f4mTester/?streamtype=TSDOWNLOADER&amp;name=Powered_By_e-Doctor_e-Modder;url=http://ksportiptv.com:1557/live/enigma10/VUNuVnnJhQ/3304.ts</link>
		
		<item>
			<title>DK: VIASAT FILM PREMIER</title>
			<link>plugin://plugin.video.f4mTester/?streamtype=TSDOWNLOADER&amp;name=Powered_By_e-Doctor_e-Modder;url=http://ksportiptv.com:1557/live/enigma10/VUNuVnnJhQ/3305.ts</link>
		
		<item>
			<title>DK: VIASAT FILM FAMILY</title>
			<link>plugin://plugin.video.f4mTester/?streamtype=TSDOWNLOADER&amp;name=Powered_By_e-Doctor_e-Modder;url=http://ksportiptv.com:1557/live/enigma10/VUNuVnnJhQ/3306.ts</link>
		
		<item>
			<title>DK: VIASAT FILM EXPLORE</title>
			<link>plugin://plugin.video.f4mTester/?streamtype=TSDOWNLOADER&amp;name=Powered_By_e-Doctor_e-Modder;url=http://ksportiptv.com:1557/live/enigma10/VUNuVnnJhQ/3308.ts</link>
		
		<item>
			<title>DK: VIASAT FILM COMEDY</title>
			<link>plugin://plugin.video.f4mTester/?streamtype=TSDOWNLOADER&amp;name=Powered_By_e-Doctor_e-Modder;url=http://ksportiptv.com:1557/live/enigma10/VUNuVnnJhQ/3307.ts</link>
		
		<item>
			<title>DK: VFILM PREMIER</title>
			<link>plugin://plugin.video.f4mTester/?streamtype=TSDOWNLOADER&amp;name=Powered_By_e-Doctor_e-Modder;url=http://ksportiptv.com:1557/live/enigma10/VUNuVnnJhQ/3309.ts</link>
		
		<item>
			<title>DK: TV6</title>
			<link>plugin://plugin.video.f4mTester/?streamtype=TSDOWNLOADER&amp;name=Powered_By_e-Doctor_e-Modder;url=http://ksportiptv.com:1557/live/enigma10/VUNuVnnJhQ/3316.ts</link>
		
		<item>
			<title>DK: TV3 SPORT 2</title>
			<link>plugin://plugin.video.f4mTester/?streamtype=TSDOWNLOADER&amp;name=Powered_By_e-Doctor_e-Modder;url=http://ksportiptv.com:1557/live/enigma10/VUNuVnnJhQ/3311.ts</link>
		
		<item>
			<title>DK: TV3 SPORT 1</title>
			<link>plugin://plugin.video.f4mTester/?streamtype=TSDOWNLOADER&amp;name=Powered_By_e-Doctor_e-Modder;url=http://ksportiptv.com:1557/live/enigma10/VUNuVnnJhQ/3310.ts</link>
		
		<item>
			<title>DK: TV3 Puls</title>
			<link>plugin://plugin.video.f4mTester/?streamtype=TSDOWNLOADER&amp;name=Powered_By_e-Doctor_e-Modder;url=http://ksportiptv.com:1557/live/enigma10/VUNuVnnJhQ/3290.ts</link>
		
		<item>
			<title>DK: TV3 Denmark</title>
			<link>plugin://plugin.video.f4mTester/?streamtype=TSDOWNLOADER&amp;name=Powered_By_e-Doctor_e-Modder;url=http://ksportiptv.com:1557/live/enigma10/VUNuVnnJhQ/3312.ts</link>
		
		<item>
			<title>DK: TV3</title>
			<link>plugin://plugin.video.f4mTester/?streamtype=TSDOWNLOADER&amp;name=Powered_By_e-Doctor_e-Modder;url=http://ksportiptv.com:1557/live/enigma10/VUNuVnnJhQ/3291.ts</link>
		
		<item>
			<title>DK: TV2 Zulu</title>
			<link>plugin://plugin.video.f4mTester/?streamtype=TSDOWNLOADER&amp;name=Powered_By_e-Doctor_e-Modder;url=http://ksportiptv.com:1557/live/enigma10/VUNuVnnJhQ/3292.ts</link>
		
		<item>
			<title>DK: TV2 Zebra</title>
			<link>plugin://plugin.video.f4mTester/?streamtype=TSDOWNLOADER&amp;name=Powered_By_e-Doctor_e-Modder;url=http://ksportiptv.com:1557/live/enigma10/VUNuVnnJhQ/3317.ts</link>
		
		<item>
			<title>DK: TV2 Sport</title>
			<link>plugin://plugin.video.f4mTester/?streamtype=TSDOWNLOADER&amp;name=Powered_By_e-Doctor_e-Modder;url=http://ksportiptv.com:1557/live/enigma10/VUNuVnnJhQ/3318.ts</link>
		
		<item>
			<title>DK: TV2 Ost</title>
			<link>plugin://plugin.video.f4mTester/?streamtype=TSDOWNLOADER&amp;name=Powered_By_e-Doctor_e-Modder;url=http://ksportiptv.com:1557/live/enigma10/VUNuVnnJhQ/3319.ts</link>
		
		<item>
			<title>DK: TV2 NORGE</title>
			<link>plugin://plugin.video.f4mTester/?streamtype=TSDOWNLOADER&amp;name=Powered_By_e-Doctor_e-Modder;url=http://ksportiptv.com:1557/live/enigma10/VUNuVnnJhQ/3320.ts</link>
		
		<item>
			<title>DK: TV2 News</title>
			<link>plugin://plugin.video.f4mTester/?streamtype=TSDOWNLOADER&amp;name=Powered_By_e-Doctor_e-Modder;url=http://ksportiptv.com:1557/live/enigma10/VUNuVnnJhQ/3293.ts</link>
		
		<item>
			<title>DK: TV2 MIDT-VEST</title>
			<link>plugin://plugin.video.f4mTester/?streamtype=TSDOWNLOADER&amp;name=Powered_By_e-Doctor_e-Modder;url=http://ksportiptv.com:1557/live/enigma10/VUNuVnnJhQ/3313.ts</link>
		
		<item>
			<title>DK: TV2 Lorry</title>
			<link>plugin://plugin.video.f4mTester/?streamtype=TSDOWNLOADER&amp;name=Powered_By_e-Doctor_e-Modder;url=http://ksportiptv.com:1557/live/enigma10/VUNuVnnJhQ/3321.ts</link>
		
		<item>
			<title>DK: TV2 Fri</title>
			<link>plugin://plugin.video.f4mTester/?streamtype=TSDOWNLOADER&amp;name=Powered_By_e-Doctor_e-Modder;url=http://ksportiptv.com:1557/live/enigma10/VUNuVnnJhQ/3294.ts</link>
		
		<item>
			<title>DK: TV2 CHARLI</title>
			<link>plugin://plugin.video.f4mTester/?streamtype=TSDOWNLOADER&amp;name=Powered_By_e-Doctor_e-Modder;url=http://ksportiptv.com:1557/live/enigma10/VUNuVnnJhQ/3314.ts</link>
		
		<item>
			<title>DK: TV Norge</title>
			<link>plugin://plugin.video.f4mTester/?streamtype=TSDOWNLOADER&amp;name=Powered_By_e-Doctor_e-Modder;url=http://ksportiptv.com:1557/live/enigma10/VUNuVnnJhQ/3315.ts</link>
		
		<item>
			<title>DK: TCM</title>
			<link>plugin://plugin.video.f4mTester/?streamtype=TSDOWNLOADER&amp;name=Powered_By_e-Doctor_e-Modder;url=http://ksportiptv.com:1557/live/enigma10/VUNuVnnJhQ/3322.ts</link>
		
		<item>
			<title>DK: Nat Geo</title>
			<link>plugin://plugin.video.f4mTester/?streamtype=TSDOWNLOADER&amp;name=Powered_By_e-Doctor_e-Modder;url=http://ksportiptv.com:1557/live/enigma10/VUNuVnnJhQ/3340.ts</link>
		
		<item>
			<title>DK: MAT</title>
			<link>plugin://plugin.video.f4mTester/?streamtype=TSDOWNLOADER&amp;name=Powered_By_e-Doctor_e-Modder;url=http://ksportiptv.com:1557/live/enigma10/VUNuVnnJhQ/3323.ts</link>
		
		<item>
			<title>DK: Kanal 9</title>
			<link>plugin://plugin.video.f4mTester/?streamtype=TSDOWNLOADER&amp;name=Powered_By_e-Doctor_e-Modder;url=http://ksportiptv.com:1557/live/enigma10/VUNuVnnJhQ/3324.ts</link>
		
		<item>
			<title>DK: Kanal 5</title>
			<link>plugin://plugin.video.f4mTester/?streamtype=TSDOWNLOADER&amp;name=Powered_By_e-Doctor_e-Modder;url=http://ksportiptv.com:1557/live/enigma10/VUNuVnnJhQ/3325.ts</link>
		
		<item>
			<title>DK: DR ULTRA</title>
			<link>plugin://plugin.video.f4mTester/?streamtype=TSDOWNLOADER&amp;name=Powered_By_e-Doctor_e-Modder;url=http://ksportiptv.com:1557/live/enigma10/VUNuVnnJhQ/3326.ts</link>
		
		<item>
			<title>DK: DR Ramasjang</title>
			<link>plugin://plugin.video.f4mTester/?streamtype=TSDOWNLOADER&amp;name=Powered_By_e-Doctor_e-Modder;url=http://ksportiptv.com:1557/live/enigma10/VUNuVnnJhQ/3327.ts</link>
		
		<item>
			<title>DK: DR K</title>
			<link>plugin://plugin.video.f4mTester/?streamtype=TSDOWNLOADER&amp;name=Powered_By_e-Doctor_e-Modder;url=http://ksportiptv.com:1557/live/enigma10/VUNuVnnJhQ/3328.ts</link>
		
		<item>
			<title>DK: DR 2</title>
			<link>plugin://plugin.video.f4mTester/?streamtype=TSDOWNLOADER&amp;name=Powered_By_e-Doctor_e-Modder;url=http://ksportiptv.com:1557/live/enigma10/VUNuVnnJhQ/3329.ts</link>
		
		<item>
			<title>DK: DR 1</title>
			<link>plugin://plugin.video.f4mTester/?streamtype=TSDOWNLOADER&amp;name=Powered_By_e-Doctor_e-Modder;url=http://ksportiptv.com:1557/live/enigma10/VUNuVnnJhQ/3330.ts</link>
		
		<item>
			<title>DK: Animal Planet HD</title>
			<link>plugin://plugin.video.f4mTester/?streamtype=TSDOWNLOADER&amp;name=Powered_By_e-Doctor_e-Modder;url=http://ksportiptv.com:1557/live/enigma10/VUNuVnnJhQ/3338.ts</link>
		
		<item>
			<title>DK: 6 Eren</title>
			<link>plugin://plugin.video.f4mTester/?streamtype=TSDOWNLOADER&amp;name=Powered_By_e-Doctor_e-Modder;url=http://ksportiptv.com:1557/live/enigma10/VUNuVnnJhQ/3339.ts</link>
		
		<item>
			<title>DK: 3 Plus</title>
			<link>plugin://plugin.video.f4mTester/?streamtype=TSDOWNLOADER&amp;name=Powered_By_e-Doctor_e-Modder;url=http://ksportiptv.com:1557/live/enigma10/VUNuVnnJhQ/3297.ts</link>
		
		<item>
			<title>DK: C More Live</title>
			<link>plugin://plugin.video.f4mTester/?streamtype=TSDOWNLOADER&amp;name=Powered_By_e-Doctor_e-Modder;url=http://ksportiptv.com:1557/live/enigma10/VUNuVnnJhQ/3335.ts</link>
		
		<item>
			<title>DK: C More Hits</title>
			<link>plugin://plugin.video.f4mTester/?streamtype=TSDOWNLOADER&amp;name=Powered_By_e-Doctor_e-Modder;url=http://ksportiptv.com:1557/live/enigma10/VUNuVnnJhQ/3341.ts</link>
		
		<item>
			<title>DK: C More Football</title>
			<link>plugin://plugin.video.f4mTester/?streamtype=TSDOWNLOADER&amp;name=Powered_By_e-Doctor_e-Modder;url=http://ksportiptv.com:1557/live/enigma10/VUNuVnnJhQ/3336.ts</link>
		
		<item>
			<title>DK: C More First</title>
			<link>plugin://plugin.video.f4mTester/?streamtype=TSDOWNLOADER&amp;name=Powered_By_e-Doctor_e-Modder;url=http://ksportiptv.com:1557/live/enigma10/VUNuVnnJhQ/3342.ts</link>
		
		<item>
			<title>DK: C More Extreme</title>
			<link>plugin://plugin.video.f4mTester/?streamtype=TSDOWNLOADER&amp;name=Powered_By_e-Doctor_e-Modder;url=http://ksportiptv.com:1557/live/enigma10/VUNuVnnJhQ/3337.ts</link>
		
		<item>
			<title>Denmark : Tv3</title>
			<link>plugin://plugin.video.f4mTester/?streamtype=TSDOWNLOADER&amp;name=Powered_By_e-Doctor_e-Modder;url=http://ksportiptv.com:1557/live/enigma10/VUNuVnnJhQ/2498.ts</link>
		
		<item>
			<title>Denmark : Tv2 Zebra</title>
			<link>plugin://plugin.video.f4mTester/?streamtype=TSDOWNLOADER&amp;name=Powered_By_e-Doctor_e-Modder;url=http://ksportiptv.com:1557/live/enigma10/VUNuVnnJhQ/2497.ts</link>
		
		<item>
			<title>Denmark : C MORE SERIES</title>
			<link>plugin://plugin.video.f4mTester/?streamtype=TSDOWNLOADER&amp;name=Powered_By_e-Doctor_e-Modder;url=http://ksportiptv.com:1557/live/enigma10/VUNuVnnJhQ/2551.ts</link>
		
		<item>
			<title>Denmark : C MORE HITS</title>
			<link>plugin://plugin.video.f4mTester/?streamtype=TSDOWNLOADER&amp;name=Powered_By_e-Doctor_e-Modder;url=http://ksportiptv.com:1557/live/enigma10/VUNuVnnJhQ/2552.ts</link>