<streamingInfos>
		<item>	
			<title>"[COLOR red][B]Powered by e-doctor[/B][/COLOR]"</title>
			<link>plugin://plugin.video.youtube/?path=/root/video&action=play_video&videoid=GA0N0Bu5JiE</link>
		<item>
			<title>"[COLOR red][B]http://e-doctor.webstarts.com[/B][/COLOR]"</title>
			<link>plugin://plugin.video.youtube/?path=/root/video&action=play_video&videoid=GA0N0Bu5JiE</link>
			
			
		<item>
			<title>"[COLOR red][B]SERVER 1[/B][/COLOR]"</title>
			<link>http://......</link>	
			
		<item>
			<title>GR: ZOUGL</title>
			<link>plugin://plugin.video.f4mTester/?streamtype=TSDOWNLOADER&amp;name=Powered_By_e-Doctor_e-Modder;url=http://iptvfree1.com:6969/live/1/www.iptvrestream.net/3305.ts</link>
		
		<item>
			<title>GR: VOULI</title>
			<link>plugin://plugin.video.f4mTester/?streamtype=TSDOWNLOADER&amp;name=Powered_By_e-Doctor_e-Modder;url=http://iptvfree1.com:6969/live/1/www.iptvrestream.net/3306.ts</link>
		
		<item>
			<title>GR: Vergina TV</title>
			<link>plugin://plugin.video.f4mTester/?streamtype=TSDOWNLOADER&amp;name=Powered_By_e-Doctor_e-Modder;url=http://iptvfree1.com:6969/live/1/www.iptvrestream.net/3333.ts</link>
		
		<item>
			<title>GR: Tv100</title>
			<link>plugin://plugin.video.f4mTester/?streamtype=TSDOWNLOADER&amp;name=Powered_By_e-Doctor_e-Modder;url=http://iptvfree1.com:6969/live/1/www.iptvrestream.net/3307.ts</link>
		
		<item>
			<title>GR: TV1 Siros</title>
			<link>plugin://plugin.video.f4mTester/?streamtype=TSDOWNLOADER&amp;name=Powered_By_e-Doctor_e-Modder;url=http://iptvfree1.com:6969/live/1/www.iptvrestream.net/3327.ts</link>
		
		<item>
			<title>GR: TV Gold</title>
			<link>plugin://plugin.video.f4mTester/?streamtype=TSDOWNLOADER&amp;name=Powered_By_e-Doctor_e-Modder;url=http://iptvfree1.com:6969/live/1/www.iptvrestream.net/3308.ts</link>
		
		<item>
			<title>GR: TV 1000</title>
			<link>plugin://plugin.video.f4mTester/?streamtype=TSDOWNLOADER&amp;name=Powered_By_e-Doctor_e-Modder;url=http://iptvfree1.com:6969/live/1/www.iptvrestream.net/3351.ts</link>
		
		<item>
			<title>GR: TRT</title>
			<link>plugin://plugin.video.f4mTester/?streamtype=TSDOWNLOADER&amp;name=Powered_By_e-Doctor_e-Modder;url=http://iptvfree1.com:6969/live/1/www.iptvrestream.net/3309.ts</link>
		
		<item>
			<title>GR: TILESPORT</title>
			<link>plugin://plugin.video.f4mTester/?streamtype=TSDOWNLOADER&amp;name=Powered_By_e-Doctor_e-Modder;url=http://iptvfree1.com:6969/live/1/www.iptvrestream.net/3310.ts</link>
		
		<item>
			<title>GR: Thraki TV</title>
			<link>plugin://plugin.video.f4mTester/?streamtype=TSDOWNLOADER&amp;name=Powered_By_e-Doctor_e-Modder;url=http://iptvfree1.com:6969/live/1/www.iptvrestream.net/3311.ts</link>
		
		<item>
			<title>GR: Thema TV</title>
			<link>plugin://plugin.video.f4mTester/?streamtype=TSDOWNLOADER&amp;name=Powered_By_e-Doctor_e-Modder;url=http://iptvfree1.com:6969/live/1/www.iptvrestream.net/3352.ts</link>
		
		<item>
			<title>GR: Start TV</title>
			<link>plugin://plugin.video.f4mTester/?streamtype=TSDOWNLOADER&amp;name=Powered_By_e-Doctor_e-Modder;url=http://iptvfree1.com:6969/live/1/www.iptvrestream.net/3312.ts</link>
		
		<item>
			<title>GR: Star TV</title>
			<link>plugin://plugin.video.f4mTester/?streamtype=TSDOWNLOADER&amp;name=Powered_By_e-Doctor_e-Modder;url=http://iptvfree1.com:6969/live/1/www.iptvrestream.net/3353.ts</link>
		
		<item>
			<title>GR: Skai</title>
			<link>plugin://plugin.video.f4mTester/?streamtype=TSDOWNLOADER&amp;name=Powered_By_e-Doctor_e-Modder;url=http://iptvfree1.com:6969/live/1/www.iptvrestream.net/3338.ts</link>
		
		<item>
			<title>GR: Sigma</title>
			<link>plugin://plugin.video.f4mTester/?streamtype=TSDOWNLOADER&amp;name=Powered_By_e-Doctor_e-Modder;url=http://iptvfree1.com:6969/live/1/www.iptvrestream.net/3339.ts</link>
		
		<item>
			<title>GR: SBC</title>
			<link>plugin://plugin.video.f4mTester/?streamtype=TSDOWNLOADER&amp;name=Powered_By_e-Doctor_e-Modder;url=http://iptvfree1.com:6969/live/1/www.iptvrestream.net/3313.ts</link>
		
		<item>
			<title>GR: SAMIAKI</title>
			<link>plugin://plugin.video.f4mTester/?streamtype=TSDOWNLOADER&amp;name=Powered_By_e-Doctor_e-Modder;url=http://iptvfree1.com:6969/live/1/www.iptvrestream.net/3314.ts</link>
		
		<item>
			<title>GR: Omega TV</title>
			<link>plugin://plugin.video.f4mTester/?streamtype=TSDOWNLOADER&amp;name=Powered_By_e-Doctor_e-Modder;url=http://iptvfree1.com:6969/live/1/www.iptvrestream.net/3340.ts</link>
		
		<item>
			<title>GR: OMEGA</title>
			<link>plugin://plugin.video.f4mTester/?streamtype=TSDOWNLOADER&amp;name=Powered_By_e-Doctor_e-Modder;url=http://iptvfree1.com:6969/live/1/www.iptvrestream.net/3315.ts</link>
		
		<item>
			<title>GR: NOVA</title>
			<link>plugin://plugin.video.f4mTester/?streamtype=TSDOWNLOADER&amp;name=Powered_By_e-Doctor_e-Modder;url=http://iptvfree1.com:6969/live/1/www.iptvrestream.net/3354.ts</link>
		
		<item>
			<title>GR: New TV</title>
			<link>plugin://plugin.video.f4mTester/?streamtype=TSDOWNLOADER&amp;name=Powered_By_e-Doctor_e-Modder;url=http://iptvfree1.com:6969/live/1/www.iptvrestream.net/3321.ts</link>
		
		<item>
			<title>GR: NEA</title>
			<link>plugin://plugin.video.f4mTester/?streamtype=TSDOWNLOADER&amp;name=Powered_By_e-Doctor_e-Modder;url=http://iptvfree1.com:6969/live/1/www.iptvrestream.net/3319.ts</link>
		
		<item>
			<title>GR: MESSINIA TV</title>
			<link>plugin://plugin.video.f4mTester/?streamtype=TSDOWNLOADER&amp;name=Powered_By_e-Doctor_e-Modder;url=http://iptvfree1.com:6969/live/1/www.iptvrestream.net/3320.ts</link>
		
		<item>
			<title>GR: Mega</title>
			<link>plugin://plugin.video.f4mTester/?streamtype=TSDOWNLOADER&amp;name=Powered_By_e-Doctor_e-Modder;url=http://iptvfree1.com:6969/live/1/www.iptvrestream.net/3341.ts</link>
		
		<item>
			<title>GR: Makeleio Web Tv</title>
			<link>plugin://plugin.video.f4mTester/?streamtype=TSDOWNLOADER&amp;name=Powered_By_e-Doctor_e-Modder;url=http://iptvfree1.com:6969/live/1/www.iptvrestream.net/3355.ts</link>
		
		<item>
			<title>GR: Makedonia</title>
			<link>plugin://plugin.video.f4mTester/?streamtype=TSDOWNLOADER&amp;name=Powered_By_e-Doctor_e-Modder;url=http://iptvfree1.com:6969/live/1/www.iptvrestream.net/3322.ts</link>
		
		<item>
			<title>GR: Lepanto</title>
			<link>plugin://plugin.video.f4mTester/?streamtype=TSDOWNLOADER&amp;name=Powered_By_e-Doctor_e-Modder;url=http://iptvfree1.com:6969/live/1/www.iptvrestream.net/3342.ts</link>
		
		<item>
			<title>GR: KRITI TV</title>
			<link>plugin://plugin.video.f4mTester/?streamtype=TSDOWNLOADER&amp;name=Powered_By_e-Doctor_e-Modder;url=http://iptvfree1.com:6969/live/1/www.iptvrestream.net/3323.ts</link>
		
		<item>
			<title>GR: KONTRA TV</title>
			<link>plugin://plugin.video.f4mTester/?streamtype=TSDOWNLOADER&amp;name=Powered_By_e-Doctor_e-Modder;url=http://iptvfree1.com:6969/live/1/www.iptvrestream.net/3324.ts</link>
		
		<item>
			<title>GR: JAYZEE</title>
			<link>plugin://plugin.video.f4mTester/?streamtype=TSDOWNLOADER&amp;name=Powered_By_e-Doctor_e-Modder;url=http://iptvfree1.com:6969/live/1/www.iptvrestream.net/3325.ts</link>
		
		<item>
			<title>GR: Hpeiros TV1</title>
			<link>plugin://plugin.video.f4mTester/?streamtype=TSDOWNLOADER&amp;name=Powered_By_e-Doctor_e-Modder;url=http://iptvfree1.com:6969/live/1/www.iptvrestream.net/3356.ts</link>
		
		<item>
			<title>GR: EXTRA</title>
			<link>plugin://plugin.video.f4mTester/?streamtype=TSDOWNLOADER&amp;name=Powered_By_e-Doctor_e-Modder;url=http://iptvfree1.com:6969/live/1/www.iptvrestream.net/3326.ts</link>
		
		<item>
			<title>GR: Eurosport 2</title>
			<link>plugin://plugin.video.f4mTester/?streamtype=TSDOWNLOADER&amp;name=Powered_By_e-Doctor_e-Modder;url=http://iptvfree1.com:6969/live/1/www.iptvrestream.net/3343.ts</link>
		
		<item>
			<title>GR: Eurosport 1</title>
			<link>plugin://plugin.video.f4mTester/?streamtype=TSDOWNLOADER&amp;name=Powered_By_e-Doctor_e-Modder;url=http://iptvfree1.com:6969/live/1/www.iptvrestream.net/3344.ts</link>
		
		<item>
			<title>GR: Euronews</title>
			<link>plugin://plugin.video.f4mTester/?streamtype=TSDOWNLOADER&amp;name=Powered_By_e-Doctor_e-Modder;url=http://iptvfree1.com:6969/live/1/www.iptvrestream.net/3316.ts</link>
		
		<item>
			<title>GR: ERT2</title>
			<link>plugin://plugin.video.f4mTester/?streamtype=TSDOWNLOADER&amp;name=Powered_By_e-Doctor_e-Modder;url=http://iptvfree1.com:6969/live/1/www.iptvrestream.net/3345.ts</link>
		
		<item>
			<title>GR: ERT1</title>
			<link>plugin://plugin.video.f4mTester/?streamtype=TSDOWNLOADER&amp;name=Powered_By_e-Doctor_e-Modder;url=http://iptvfree1.com:6969/live/1/www.iptvrestream.net/3346.ts</link>
		
		<item>
			<title>GR: ERT 3</title>
			<link>plugin://plugin.video.f4mTester/?streamtype=TSDOWNLOADER&amp;name=Powered_By_e-Doctor_e-Modder;url=http://iptvfree1.com:6969/live/1/www.iptvrestream.net/3347.ts</link>
		
		<item>
			<title>GR: EPIRUS TV1</title>
			<link>plugin://plugin.video.f4mTester/?streamtype=TSDOWNLOADER&amp;name=Powered_By_e-Doctor_e-Modder;url=http://iptvfree1.com:6969/live/1/www.iptvrestream.net/3357.ts</link>
		
		<item>
			<title>GR: Ellinikosfm TV</title>
			<link>plugin://plugin.video.f4mTester/?streamtype=TSDOWNLOADER&amp;name=Powered_By_e-Doctor_e-Modder;url=http://iptvfree1.com:6969/live/1/www.iptvrestream.net/3328.ts</link>
		
		<item>
			<title>GR: E</title>
			<link>plugin://plugin.video.f4mTester/?streamtype=TSDOWNLOADER&amp;name=Powered_By_e-Doctor_e-Modder;url=http://iptvfree1.com:6969/live/1/www.iptvrestream.net/3348.ts</link>
		
		<item>
			<title>GR: DIKTYO</title>
			<link>plugin://plugin.video.f4mTester/?streamtype=TSDOWNLOADER&amp;name=Powered_By_e-Doctor_e-Modder;url=http://iptvfree1.com:6969/live/1/www.iptvrestream.net/3358.ts</link>
		
		<item>
			<title>GR: DIAVATA TV</title>
			<link>plugin://plugin.video.f4mTester/?streamtype=TSDOWNLOADER&amp;name=Powered_By_e-Doctor_e-Modder;url=http://iptvfree1.com:6969/live/1/www.iptvrestream.net/3317.ts</link>
		
		<item>
			<title>GR: BLUE SKY</title>
			<link>plugin://plugin.video.f4mTester/?streamtype=TSDOWNLOADER&amp;name=Powered_By_e-Doctor_e-Modder;url=http://iptvfree1.com:6969/live/1/www.iptvrestream.net/3329.ts</link>
		
		<item>
			<title>GR: Axeloos TV</title>
			<link>plugin://plugin.video.f4mTester/?streamtype=TSDOWNLOADER&amp;name=Powered_By_e-Doctor_e-Modder;url=http://iptvfree1.com:6969/live/1/www.iptvrestream.net/3330.ts</link>
		
		<item>
			<title>GR: Astra</title>
			<link>plugin://plugin.video.f4mTester/?streamtype=TSDOWNLOADER&amp;name=Powered_By_e-Doctor_e-Modder;url=http://iptvfree1.com:6969/live/1/www.iptvrestream.net/3331.ts</link>
		
		<item>
			<title>GR: Art</title>
			<link>plugin://plugin.video.f4mTester/?streamtype=TSDOWNLOADER&amp;name=Powered_By_e-Doctor_e-Modder;url=http://iptvfree1.com:6969/live/1/www.iptvrestream.net/3332.ts</link>
		
		<item>
			<title>GR: Apeiro TV</title>
			<link>plugin://plugin.video.f4mTester/?streamtype=TSDOWNLOADER&amp;name=Powered_By_e-Doctor_e-Modder;url=http://iptvfree1.com:6969/live/1/www.iptvrestream.net/3359.ts</link>
		
		<item>
			<title>GR: ANT1</title>
			<link>plugin://plugin.video.f4mTester/?streamtype=TSDOWNLOADER&amp;name=Powered_By_e-Doctor_e-Modder;url=http://iptvfree1.com:6969/live/1/www.iptvrestream.net/3349.ts</link>
		
		<item>
			<title>GR: Alpha</title>
			<link>plugin://plugin.video.f4mTester/?streamtype=TSDOWNLOADER&amp;name=Powered_By_e-Doctor_e-Modder;url=http://iptvfree1.com:6969/live/1/www.iptvrestream.net/3350.ts</link>
		
		<item>
			<title>GR: AIGAIO TV</title>
			<link>plugin://plugin.video.f4mTester/?streamtype=TSDOWNLOADER&amp;name=Powered_By_e-Doctor_e-Modder;url=http://iptvfree1.com:6969/live/1/www.iptvrestream.net/3334.ts</link>
		
		<item>
			<title>GR: ACTION 24</title>
			<link>plugin://plugin.video.f4mTester/?streamtype=TSDOWNLOADER&amp;name=Powered_By_e-Doctor_e-Modder;url=http://iptvfree1.com:6969/live/1/www.iptvrestream.net/3335.ts</link>
		
		<item>
			<title>GR: 4E Star</title>
			<link>plugin://plugin.video.f4mTester/?streamtype=TSDOWNLOADER&amp;name=Powered_By_e-Doctor_e-Modder;url=http://iptvfree1.com:6969/live/1/www.iptvrestream.net/3337.ts</link>
		
		<item>
			<title>GR: 4E</title>
			<link>plugin://plugin.video.f4mTester/?streamtype=TSDOWNLOADER&amp;name=Powered_By_e-Doctor_e-Modder;url=http://iptvfree1.com:6969/live/1/www.iptvrestream.net/3336.ts</link>
		
		<item>
			<title>GR : TV Mytilini</title>
			<link>plugin://plugin.video.f4mTester/?streamtype=TSDOWNLOADER&amp;name=Powered_By_e-Doctor_e-Modder;url=http://iptvfree1.com:6969/live/1/www.iptvrestream.net/3318.ts</link>
		
		<item>
			<title>GR: ZOUGLA</title>
			<link>plugin://plugin.video.f4mTester/?streamtype=TSDOWNLOADER&amp;name=Powered_By_e-Doctor_e-Modder;url=http://iptvfree1.com:6969/live/1/www.iptvrestream.net/3658.ts</link>
		
		<item>
			<title>GR: Vouli TV</title>
			<link>plugin://plugin.video.f4mTester/?streamtype=TSDOWNLOADER&amp;name=Powered_By_e-Doctor_e-Modder;url=http://iptvfree1.com:6969/live/1/www.iptvrestream.net/3657.ts</link>
		
		<item>
			<title>GR: Star</title>
			<link>plugin://plugin.video.f4mTester/?streamtype=TSDOWNLOADER&amp;name=Powered_By_e-Doctor_e-Modder;url=http://iptvfree1.com:6969/live/1/www.iptvrestream.net/3654.ts</link>
		
		<item>
			<title>GR: Smile</title>
			<link>plugin://plugin.video.f4mTester/?streamtype=TSDOWNLOADER&amp;name=Powered_By_e-Doctor_e-Modder;url=http://iptvfree1.com:6969/live/1/www.iptvrestream.net/3653.ts</link>
		
		<item>
			<title>GR: Sigma Cyprus</title>
			<link>plugin://plugin.video.f4mTester/?streamtype=TSDOWNLOADER&amp;name=Powered_By_e-Doctor_e-Modder;url=http://iptvfree1.com:6969/live/1/www.iptvrestream.net/3652.ts</link>
		
		<item>
			<title>GR: Rik Sat</title>
			<link>plugin://plugin.video.f4mTester/?streamtype=TSDOWNLOADER&amp;name=Powered_By_e-Doctor_e-Modder;url=http://iptvfree1.com:6969/live/1/www.iptvrestream.net/3650.ts</link>
		
		<item>
			<title>GR: Rik</title>
			<link>plugin://plugin.video.f4mTester/?streamtype=TSDOWNLOADER&amp;name=Powered_By_e-Doctor_e-Modder;url=http://iptvfree1.com:6969/live/1/www.iptvrestream.net/3649.ts</link>
		
		<item>
			<title>GR: Nickelodeon</title>
			<link>plugin://plugin.video.f4mTester/?streamtype=TSDOWNLOADER&amp;name=Powered_By_e-Doctor_e-Modder;url=http://iptvfree1.com:6969/live/1/www.iptvrestream.net/3648.ts</link>
		
		<item>
			<title>GR: Nea Tv</title>
			<link>plugin://plugin.video.f4mTester/?streamtype=TSDOWNLOADER&amp;name=Powered_By_e-Doctor_e-Modder;url=http://iptvfree1.com:6969/live/1/www.iptvrestream.net/3647.ts</link>
		
		<item>
			<title>GR: Nat Geo</title>
			<link>plugin://plugin.video.f4mTester/?streamtype=TSDOWNLOADER&amp;name=Powered_By_e-Doctor_e-Modder;url=http://iptvfree1.com:6969/live/1/www.iptvrestream.net/3675.ts</link>
		
		<item>
			<title>GR: MTVeece</title>
			<link>plugin://plugin.video.f4mTester/?streamtype=TSDOWNLOADER&amp;name=Powered_By_e-Doctor_e-Modder;url=http://iptvfree1.com:6969/live/1/www.iptvrestream.net/3646.ts</link>
		
		<item>
			<title>GR: Mega Delay</title>
			<link>plugin://plugin.video.f4mTester/?streamtype=TSDOWNLOADER&amp;name=Powered_By_e-Doctor_e-Modder;url=http://iptvfree1.com:6969/live/1/www.iptvrestream.net/3645.ts</link>
		
		<item>
			<title>GR: Mega Cyprus</title>
			<link>plugin://plugin.video.f4mTester/?streamtype=TSDOWNLOADER&amp;name=Powered_By_e-Doctor_e-Modder;url=http://iptvfree1.com:6969/live/1/www.iptvrestream.net/3644.ts</link>
		
		<item>
			<title>GR: Mega Cosmo</title>
			<link>plugin://plugin.video.f4mTester/?streamtype=TSDOWNLOADER&amp;name=Powered_By_e-Doctor_e-Modder;url=http://iptvfree1.com:6969/live/1/www.iptvrestream.net/3643.ts</link>
		
		<item>
			<title>GR: Makedonia TV Delay</title>
			<link>plugin://plugin.video.f4mTester/?streamtype=TSDOWNLOADER&amp;name=Powered_By_e-Doctor_e-Modder;url=http://iptvfree1.com:6969/live/1/www.iptvrestream.net/3642.ts</link>
		
		<item>
			<title>GR: Makedonia TV</title>
			<link>plugin://plugin.video.f4mTester/?streamtype=TSDOWNLOADER&amp;name=Powered_By_e-Doctor_e-Modder;url=http://iptvfree1.com:6969/live/1/www.iptvrestream.net/3641.ts</link>
		
		<item>
			<title>GR: Mad TV</title>
			<link>plugin://plugin.video.f4mTester/?streamtype=TSDOWNLOADER&amp;name=Powered_By_e-Doctor_e-Modder;url=http://iptvfree1.com:6969/live/1/www.iptvrestream.net/3640.ts</link>
		
		<item>
			<title>GR: Lyxnoc</title>
			<link>plugin://plugin.video.f4mTester/?streamtype=TSDOWNLOADER&amp;name=Powered_By_e-Doctor_e-Modder;url=http://iptvfree1.com:6969/live/1/www.iptvrestream.net/3655.ts</link>
		
		<item>
			<title>GR: Krhth TV</title>
			<link>plugin://plugin.video.f4mTester/?streamtype=TSDOWNLOADER&amp;name=Powered_By_e-Doctor_e-Modder;url=http://iptvfree1.com:6969/live/1/www.iptvrestream.net/3639.ts</link>
		
		<item>
			<title>GR: Kontra Channel</title>
			<link>plugin://plugin.video.f4mTester/?streamtype=TSDOWNLOADER&amp;name=Powered_By_e-Doctor_e-Modder;url=http://iptvfree1.com:6969/live/1/www.iptvrestream.net/3638.ts</link>
		
		<item>
			<title>GR: High TV</title>
			<link>plugin://plugin.video.f4mTester/?streamtype=TSDOWNLOADER&amp;name=Powered_By_e-Doctor_e-Modder;url=http://iptvfree1.com:6969/live/1/www.iptvrestream.net/3637.ts</link>
		
		<item>
			<title>GR: Extra Channel</title>
			<link>plugin://plugin.video.f4mTester/?streamtype=TSDOWNLOADER&amp;name=Powered_By_e-Doctor_e-Modder;url=http://iptvfree1.com:6969/live/1/www.iptvrestream.net/3636.ts</link>
		
		<item>
			<title>GR: Ert HD Delay</title>
			<link>plugin://plugin.video.f4mTester/?streamtype=TSDOWNLOADER&amp;name=Powered_By_e-Doctor_e-Modder;url=http://iptvfree1.com:6969/live/1/www.iptvrestream.net/3671.ts</link>
		
		<item>
			<title>GR: Ert HD</title>
			<link>plugin://plugin.video.f4mTester/?streamtype=TSDOWNLOADER&amp;name=Powered_By_e-Doctor_e-Modder;url=http://iptvfree1.com:6969/live/1/www.iptvrestream.net/3670.ts</link>
		
		<item>
			<title>GR: Ert 2</title>
			<link>plugin://plugin.video.f4mTester/?streamtype=TSDOWNLOADER&amp;name=Powered_By_e-Doctor_e-Modder;url=http://iptvfree1.com:6969/live/1/www.iptvrestream.net/3674.ts</link>
		
		<item>
			<title>GR: Ert 1</title>
			<link>plugin://plugin.video.f4mTester/?streamtype=TSDOWNLOADER&amp;name=Powered_By_e-Doctor_e-Modder;url=http://iptvfree1.com:6969/live/1/www.iptvrestream.net/3672.ts</link>
		
		<item>
			<title>GR: Epsilon Delay</title>
			<link>plugin://plugin.video.f4mTester/?streamtype=TSDOWNLOADER&amp;name=Powered_By_e-Doctor_e-Modder;url=http://iptvfree1.com:6969/live/1/www.iptvrestream.net/3633.ts</link>
		
		<item>
			<title>GR: Epsilon</title>
			<link>plugin://plugin.video.f4mTester/?streamtype=TSDOWNLOADER&amp;name=Powered_By_e-Doctor_e-Modder;url=http://iptvfree1.com:6969/live/1/www.iptvrestream.net/3635.ts</link>
		
		<item>
			<title>GR: Epirus TV</title>
			<link>plugin://plugin.video.f4mTester/?streamtype=TSDOWNLOADER&amp;name=Powered_By_e-Doctor_e-Modder;url=http://iptvfree1.com:6969/live/1/www.iptvrestream.net/3634.ts</link>
		
		<item>
			<title>GR: Diktyo TV</title>
			<link>plugin://plugin.video.f4mTester/?streamtype=TSDOWNLOADER&amp;name=Powered_By_e-Doctor_e-Modder;url=http://iptvfree1.com:6969/live/1/www.iptvrestream.net/3669.ts</link>
		
		<item>
			<title>GR: Channel 9</title>
			<link>plugin://plugin.video.f4mTester/?streamtype=TSDOWNLOADER&amp;name=Powered_By_e-Doctor_e-Modder;url=http://iptvfree1.com:6969/live/1/www.iptvrestream.net/3668.ts</link>
		
		<item>
			<title>GR: Boyah</title>
			<link>plugin://plugin.video.f4mTester/?streamtype=TSDOWNLOADER&amp;name=Powered_By_e-Doctor_e-Modder;url=http://iptvfree1.com:6969/live/1/www.iptvrestream.net/3651.ts</link>
		
		<item>
			<title>GR: Attica TV</title>
			<link>plugin://plugin.video.f4mTester/?streamtype=TSDOWNLOADER&amp;name=Powered_By_e-Doctor_e-Modder;url=http://iptvfree1.com:6969/live/1/www.iptvrestream.net/3667.ts</link>
		
		<item>
			<title>GR: APT</title>
			<link>plugin://plugin.video.f4mTester/?streamtype=TSDOWNLOADER&amp;name=Powered_By_e-Doctor_e-Modder;url=http://iptvfree1.com:6969/live/1/www.iptvrestream.net/3673.ts</link>
		
		<item>
			<title>GR: Apeiro</title>
			<link>plugin://plugin.video.f4mTester/?streamtype=TSDOWNLOADER&amp;name=Powered_By_e-Doctor_e-Modder;url=http://iptvfree1.com:6969/live/1/www.iptvrestream.net/3666.ts</link>
		
		<item>
			<title>GR: Ant1 Sat Delay</title>
			<link>plugin://plugin.video.f4mTester/?streamtype=TSDOWNLOADER&amp;name=Powered_By_e-Doctor_e-Modder;url=http://iptvfree1.com:6969/live/1/www.iptvrestream.net/3665.ts</link>
		
		<item>
			<title>GR: Ant1 Cyprus</title>
			<link>plugin://plugin.video.f4mTester/?streamtype=TSDOWNLOADER&amp;name=Powered_By_e-Doctor_e-Modder;url=http://iptvfree1.com:6969/live/1/www.iptvrestream.net/3663.ts</link>
		
		<item>
			<title>GR: Ant Delay</title>
			<link>plugin://plugin.video.f4mTester/?streamtype=TSDOWNLOADER&amp;name=Powered_By_e-Doctor_e-Modder;url=http://iptvfree1.com:6969/live/1/www.iptvrestream.net/3662.ts</link>
		
		<item>
			<title>GR: Alpha Sat</title>
			<link>plugin://plugin.video.f4mTester/?streamtype=TSDOWNLOADER&amp;name=Powered_By_e-Doctor_e-Modder;url=http://iptvfree1.com:6969/live/1/www.iptvrestream.net/3661.ts</link>
		
		<item>
			<title>GR: Alpha Delay</title>
			<link>plugin://plugin.video.f4mTester/?streamtype=TSDOWNLOADER&amp;name=Powered_By_e-Doctor_e-Modder;url=http://iptvfree1.com:6969/live/1/www.iptvrestream.net/3660.ts</link>
		
		<item>
			<title>GR: AB Channel</title>
			<link>plugin://plugin.video.f4mTester/?streamtype=TSDOWNLOADER&amp;name=Powered_By_e-Doctor_e-Modder;url=http://iptvfree1.com:6969/live/1/www.iptvrestream.net/3659.ts</link>
		
	
			
			
			
			
			
			
			
			
			
			
			
			
			
			
			
			
			

			
			
		<item>
			<title>"[COLOR red][B]SERVER 2[/B][/COLOR]"</title>
			<link>http://......</link>	
			
		<item>
			<title>GR: ZOUGLA</title>
			<link>plugin://plugin.video.f4mTester/?streamtype=TSDOWNLOADER&amp;name=Powered_By_e-Doctor_e-Modder;url=http://tvohnekabelundsat.levbus.de:8000/live/a.k/a.k/7156.ts</link>
		
		<item>
			<title>GR-: VOULI</title>
			<link>plugin://plugin.video.f4mTester/?streamtype=TSDOWNLOADER&amp;name=Powered_By_e-Doctor_e-Modder;url=http://tvohnekabelundsat.levbus.de:8000/live/a.k/a.k/7153.ts</link>
		
		<item>
			<title>GR: TV-100</title>
			<link>plugin://plugin.video.f4mTester/?streamtype=TSDOWNLOADER&amp;name=Powered_By_e-Doctor_e-Modder;url=http://tvohnekabelundsat.levbus.de:8000/live/a.k/a.k/7152.ts</link>
		
		<item>
			<title>GR: RIK SAT 2 TV</title>
			<link>plugin://plugin.video.f4mTester/?streamtype=TSDOWNLOADER&amp;name=Powered_By_e-Doctor_e-Modder;url=http://tvohnekabelundsat.levbus.de:8000/live/a.k/a.k/6596.ts</link>
		
		<item>
			<title>-GR: MAD TV</title>
			<link>plugin://plugin.video.f4mTester/?streamtype=TSDOWNLOADER&amp;name=Powered_By_e-Doctor_e-Modder;url=http://tvohnekabelundsat.levbus.de:8000/live/a.k/a.k/7138.ts</link>
		
		<item>
			<title>GR: KPHTH TV GR</title>
			<link>plugin://plugin.video.f4mTester/?streamtype=TSDOWNLOADER&amp;name=Powered_By_e-Doctor_e-Modder;url=http://tvohnekabelundsat.levbus.de:8000/live/a.k/a.k/7163.ts</link>
		
		<item>
			<title>GR: EBS PLUS</title>
			<link>plugin://plugin.video.f4mTester/?streamtype=TSDOWNLOADER&amp;name=Powered_By_e-Doctor_e-Modder;url=http://tvohnekabelundsat.levbus.de:8000/live/a.k/a.k/7127.ts</link>
		
		<item>
			<title>GR: CRETA WEB TV</title>
			<link>plugin://plugin.video.f4mTester/?streamtype=TSDOWNLOADER&amp;name=Powered_By_e-Doctor_e-Modder;url=http://tvohnekabelundsat.levbus.de:8000/live/a.k/a.k/7123.ts</link>
		
		<item>
			<title>GR-: ANT 1 CYP</title>
			<link>plugin://plugin.video.f4mTester/?streamtype=TSDOWNLOADER&amp;name=Powered_By_e-Doctor_e-Modder;url=http://tvohnekabelundsat.levbus.de:8000/live/a.k/a.k/7118.ts</link>
		
		<item>
			<title>GR: Zougla TV</title>
			<link>plugin://plugin.video.f4mTester/?streamtype=TSDOWNLOADER&amp;name=Powered_By_e-Doctor_e-Modder;url=http://tvohnekabelundsat.levbus.de:8000/live/a.k/a.k/4714.ts</link>
		
		<item>
			<title>GR: MEGA CYP</title>
			<link>plugin://plugin.video.f4mTester/?streamtype=TSDOWNLOADER&amp;name=Powered_By_e-Doctor_e-Modder;url=http://tvohnekabelundsat.levbus.de:8000/live/a.k/a.k/4720.ts</link>
		
		<item>
			<title>GR: KRHTH TV</title>
			<link>plugin://plugin.video.f4mTester/?streamtype=TSDOWNLOADER&amp;name=Powered_By_e-Doctor_e-Modder;url=http://tvohnekabelundsat.levbus.de:8000/live/a.k/a.k/4722.ts</link>
		
		<item>
			<title>GR-: KONTRA TV</title>
			<link>plugin://plugin.video.f4mTester/?streamtype=TSDOWNLOADER&amp;name=Powered_By_e-Doctor_e-Modder;url=http://tvohnekabelundsat.levbus.de:8000/live/a.k/a.k/4723.ts</link>
		
		<item>
			<title>GR: EXTRA 3</title>
			<link>plugin://plugin.video.f4mTester/?streamtype=TSDOWNLOADER&amp;name=Powered_By_e-Doctor_e-Modder;url=http://tvohnekabelundsat.levbus.de:8000/live/a.k/a.k/4725.ts</link>
		
		<item>
			<title>GR-: EXTRA</title>
			<link>plugin://plugin.video.f4mTester/?streamtype=TSDOWNLOADER&amp;name=Powered_By_e-Doctor_e-Modder;url=http://tvohnekabelundsat.levbus.de:8000/live/a.k/a.k/4726.ts</link>
		
		<item>
			<title>-GR: ERT 2</title>
			<link>plugin://plugin.video.f4mTester/?streamtype=TSDOWNLOADER&amp;name=Powered_By_e-Doctor_e-Modder;url=http://tvohnekabelundsat.levbus.de:8000/live/a.k/a.k/4710.ts</link>
		
		<item>
			<title>-GR: ERT 3</title>
			<link>plugin://plugin.video.f4mTester/?streamtype=TSDOWNLOADER&amp;name=Powered_By_e-Doctor_e-Modder;url=http://tvohnekabelundsat.levbus.de:8000/live/a.k/a.k/4709.ts</link>
		
		<item>
			<title>GR-: ALPHA CYP</title>
			<link>plugin://plugin.video.f4mTester/?streamtype=TSDOWNLOADER&amp;name=Powered_By_e-Doctor_e-Modder;url=http://tvohnekabelundsat.levbus.de:8000/live/a.k/a.k/4730.ts</link>
		
		<item>
			<title>GR: TV 100</title>
			<link>plugin://plugin.video.f4mTester/?streamtype=TSDOWNLOADER&amp;name=Powered_By_e-Doctor_e-Modder;url=http://tvohnekabelundsat.levbus.de:8000/live/a.k/a.k/6180.ts</link>
		
		<item>
			<title>GR: MAD TV</title>
			<link>plugin://plugin.video.f4mTester/?streamtype=TSDOWNLOADER&amp;name=Powered_By_e-Doctor_e-Modder;url=http://tvohnekabelundsat.levbus.de:8000/live/a.k/a.k/6012.ts</link>
		
		<item>
			<title>GR: EURONEWS</title>
			<link>plugin://plugin.video.f4mTester/?streamtype=TSDOWNLOADER&amp;name=Powered_By_e-Doctor_e-Modder;url=http://tvohnekabelundsat.levbus.de:8000/live/a.k/a.k/6172.ts</link>
		
		<item>
			<title>GR: EBS</title>
			<link>plugin://plugin.video.f4mTester/?streamtype=TSDOWNLOADER&amp;name=Powered_By_e-Doctor_e-Modder;url=http://tvohnekabelundsat.levbus.de:8000/live/a.k/a.k/6176.ts</link>
		
		<item>
			<title>GR: 4E</title>
			<link>plugin://plugin.video.f4mTester/?streamtype=TSDOWNLOADER&amp;name=Powered_By_e-Doctor_e-Modder;url=http://tvohnekabelundsat.levbus.de:8000/live/a.k/a.k/6161.ts</link>
		
		<item>
			<title>GR: AXELOOS TV</title>
			<link>plugin://plugin.video.f4mTester/?streamtype=TSDOWNLOADER&amp;name=Powered_By_e-Doctor_e-Modder;url=http://tvohnekabelundsat.levbus.de:8000/live/a.k/a.k/11657.ts</link>
		
		<item>
			<title>GR: SIGMA CYP</title>
			<link>plugin://plugin.video.f4mTester/?streamtype=TSDOWNLOADER&amp;name=Powered_By_e-Doctor_e-Modder;url=http://tvohnekabelundsat.levbus.de:8000/live/a.k/a.k/12056.ts</link>
		
		<item>
			<title>GR-: ERT 1</title>
			<link>plugin://plugin.video.f4mTester/?streamtype=TSDOWNLOADER&amp;name=Powered_By_e-Doctor_e-Modder;url=http://tvohnekabelundsat.levbus.de:8000/live/a.k/a.k/11945.ts</link>
		
		<item>
			<title>GR: SBC HD</title>
			<link>plugin://plugin.video.f4mTester/?streamtype=TSDOWNLOADER&amp;name=Powered_By_e-Doctor_e-Modder;url=http://tvohnekabelundsat.levbus.de:8000/live/a.k/a.k/12218.ts</link>
		
		<item>
			<title>GR: MESSINIA TV HD</title>
			<link>plugin://plugin.video.f4mTester/?streamtype=TSDOWNLOADER&amp;name=Powered_By_e-Doctor_e-Modder;url=http://tvohnekabelundsat.levbus.de:8000/live/a.k/a.k/12219.ts</link>
		
		<item>
			<title>GR-: ERT 3</title>
			<link>plugin://plugin.video.f4mTester/?streamtype=TSDOWNLOADER&amp;name=Powered_By_e-Doctor_e-Modder;url=http://tvohnekabelundsat.levbus.de:8000/live/a.k/a.k/15850.ts</link>
		
		<item>
			<title>GR-: ERT 2</title>
			<link>plugin://plugin.video.f4mTester/?streamtype=TSDOWNLOADER&amp;name=Powered_By_e-Doctor_e-Modder;url=http://tvohnekabelundsat.levbus.de:8000/live/a.k/a.k/15849.ts</link>
		
		<item>
			<title>GR: ZOUGLA</title>
			<link>plugin://plugin.video.f4mTester/?streamtype=TSDOWNLOADER&amp;name=Powered_By_e-Doctor_e-Modder;url=http://tvohnekabelundsat.levbus.de:8000/live/a.k/a.k/7156.ts</link>
		
		<item>
			<title>GR-: VOULI</title>
			<link>plugin://plugin.video.f4mTester/?streamtype=TSDOWNLOADER&amp;name=Powered_By_e-Doctor_e-Modder;url=http://tvohnekabelundsat.levbus.de:8000/live/a.k/a.k/7153.ts</link>
		
		<item>
			<title>GR: TV-100</title>
			<link>plugin://plugin.video.f4mTester/?streamtype=TSDOWNLOADER&amp;name=Powered_By_e-Doctor_e-Modder;url=http://tvohnekabelundsat.levbus.de:8000/live/a.k/a.k/7152.ts</link>
		
		<item>
			<title>GR: RIK SAT 2 TV</title>
			<link>plugin://plugin.video.f4mTester/?streamtype=TSDOWNLOADER&amp;name=Powered_By_e-Doctor_e-Modder;url=http://tvohnekabelundsat.levbus.de:8000/live/a.k/a.k/6596.ts</link>
		
		<item>
			<title>-GR: MAD TV</title>
			<link>plugin://plugin.video.f4mTester/?streamtype=TSDOWNLOADER&amp;name=Powered_By_e-Doctor_e-Modder;url=http://tvohnekabelundsat.levbus.de:8000/live/a.k/a.k/7138.ts</link>
		
		<item>
			<title>GR: KPHTH TV GR</title>
			<link>plugin://plugin.video.f4mTester/?streamtype=TSDOWNLOADER&amp;name=Powered_By_e-Doctor_e-Modder;url=http://tvohnekabelundsat.levbus.de:8000/live/a.k/a.k/7163.ts</link>
		
		<item>
			<title>GR: EBS PLUS</title>
			<link>plugin://plugin.video.f4mTester/?streamtype=TSDOWNLOADER&amp;name=Powered_By_e-Doctor_e-Modder;url=http://tvohnekabelundsat.levbus.de:8000/live/a.k/a.k/7127.ts</link>
		
		<item>
			<title>GR: CRETA WEB TV</title>
			<link>plugin://plugin.video.f4mTester/?streamtype=TSDOWNLOADER&amp;name=Powered_By_e-Doctor_e-Modder;url=http://tvohnekabelundsat.levbus.de:8000/live/a.k/a.k/7123.ts</link>
		
		<item>
			<title>GR-: ANT 1 CYP</title>
			<link>plugin://plugin.video.f4mTester/?streamtype=TSDOWNLOADER&amp;name=Powered_By_e-Doctor_e-Modder;url=http://tvohnekabelundsat.levbus.de:8000/live/a.k/a.k/7118.ts</link>
		
		<item>
			<title>GR: Zougla TV</title>
			<link>plugin://plugin.video.f4mTester/?streamtype=TSDOWNLOADER&amp;name=Powered_By_e-Doctor_e-Modder;url=http://tvohnekabelundsat.levbus.de:8000/live/a.k/a.k/4714.ts</link>
		
		<item>
			<title>GR: MEGA CYP</title>
			<link>plugin://plugin.video.f4mTester/?streamtype=TSDOWNLOADER&amp;name=Powered_By_e-Doctor_e-Modder;url=http://tvohnekabelundsat.levbus.de:8000/live/a.k/a.k/4720.ts</link>
		
		<item>
			<title>GR: KRHTH TV</title>
			<link>plugin://plugin.video.f4mTester/?streamtype=TSDOWNLOADER&amp;name=Powered_By_e-Doctor_e-Modder;url=http://tvohnekabelundsat.levbus.de:8000/live/a.k/a.k/4722.ts</link>
		
		<item>
			<title>GR-: KONTRA TV</title>
			<link>plugin://plugin.video.f4mTester/?streamtype=TSDOWNLOADER&amp;name=Powered_By_e-Doctor_e-Modder;url=http://tvohnekabelundsat.levbus.de:8000/live/a.k/a.k/4723.ts</link>
		
		<item>
			<title>GR: EXTRA 3</title>
			<link>plugin://plugin.video.f4mTester/?streamtype=TSDOWNLOADER&amp;name=Powered_By_e-Doctor_e-Modder;url=http://tvohnekabelundsat.levbus.de:8000/live/a.k/a.k/4725.ts</link>
		
		<item>
			<title>GR-: EXTRA</title>
			<link>plugin://plugin.video.f4mTester/?streamtype=TSDOWNLOADER&amp;name=Powered_By_e-Doctor_e-Modder;url=http://tvohnekabelundsat.levbus.de:8000/live/a.k/a.k/4726.ts</link>
		
		<item>
			<title>-GR: ERT 2</title>
			<link>plugin://plugin.video.f4mTester/?streamtype=TSDOWNLOADER&amp;name=Powered_By_e-Doctor_e-Modder;url=http://tvohnekabelundsat.levbus.de:8000/live/a.k/a.k/4710.ts</link>
		
		<item>
			<title>-GR: ERT 3</title>
			<link>plugin://plugin.video.f4mTester/?streamtype=TSDOWNLOADER&amp;name=Powered_By_e-Doctor_e-Modder;url=http://tvohnekabelundsat.levbus.de:8000/live/a.k/a.k/4709.ts</link>
		
		<item>
			<title>GR-: ALPHA CYP</title>
			<link>plugin://plugin.video.f4mTester/?streamtype=TSDOWNLOADER&amp;name=Powered_By_e-Doctor_e-Modder;url=http://tvohnekabelundsat.levbus.de:8000/live/a.k/a.k/4730.ts</link>
		
		<item>
			<title>GR: TV 100</title>
			<link>plugin://plugin.video.f4mTester/?streamtype=TSDOWNLOADER&amp;name=Powered_By_e-Doctor_e-Modder;url=http://tvohnekabelundsat.levbus.de:8000/live/a.k/a.k/6180.ts</link>
		
		<item>
			<title>GR: MAD TV</title>
			<link>plugin://plugin.video.f4mTester/?streamtype=TSDOWNLOADER&amp;name=Powered_By_e-Doctor_e-Modder;url=http://tvohnekabelundsat.levbus.de:8000/live/a.k/a.k/6012.ts</link>
		
		<item>
			<title>GR: EURONEWS</title>
			<link>plugin://plugin.video.f4mTester/?streamtype=TSDOWNLOADER&amp;name=Powered_By_e-Doctor_e-Modder;url=http://tvohnekabelundsat.levbus.de:8000/live/a.k/a.k/6172.ts</link>
		
		<item>
			<title>GR: EBS</title>
			<link>plugin://plugin.video.f4mTester/?streamtype=TSDOWNLOADER&amp;name=Powered_By_e-Doctor_e-Modder;url=http://tvohnekabelundsat.levbus.de:8000/live/a.k/a.k/6176.ts</link>
		
		<item>
			<title>GR: 4E</title>
			<link>plugin://plugin.video.f4mTester/?streamtype=TSDOWNLOADER&amp;name=Powered_By_e-Doctor_e-Modder;url=http://tvohnekabelundsat.levbus.de:8000/live/a.k/a.k/6161.ts</link>
		
		<item>
			<title>GR: AXELOOS TV</title>
			<link>plugin://plugin.video.f4mTester/?streamtype=TSDOWNLOADER&amp;name=Powered_By_e-Doctor_e-Modder;url=http://tvohnekabelundsat.levbus.de:8000/live/a.k/a.k/11657.ts</link>
		
		<item>
			<title>GR: SIGMA CYP</title>
			<link>plugin://plugin.video.f4mTester/?streamtype=TSDOWNLOADER&amp;name=Powered_By_e-Doctor_e-Modder;url=http://tvohnekabelundsat.levbus.de:8000/live/a.k/a.k/12056.ts</link>
		
		<item>
			<title>GR-: ERT 1</title>
			<link>plugin://plugin.video.f4mTester/?streamtype=TSDOWNLOADER&amp;name=Powered_By_e-Doctor_e-Modder;url=http://tvohnekabelundsat.levbus.de:8000/live/a.k/a.k/11945.ts</link>
		
		<item>
			<title>GR: SBC HD</title>
			<link>plugin://plugin.video.f4mTester/?streamtype=TSDOWNLOADER&amp;name=Powered_By_e-Doctor_e-Modder;url=http://tvohnekabelundsat.levbus.de:8000/live/a.k/a.k/12218.ts</link>
		
		<item>
			<title>GR: MESSINIA TV HD</title>
			<link>plugin://plugin.video.f4mTester/?streamtype=TSDOWNLOADER&amp;name=Powered_By_e-Doctor_e-Modder;url=http://tvohnekabelundsat.levbus.de:8000/live/a.k/a.k/12219.ts</link>
		
		<item>
			<title>GR-: ERT 3</title>
			<link>plugin://plugin.video.f4mTester/?streamtype=TSDOWNLOADER&amp;name=Powered_By_e-Doctor_e-Modder;url=http://tvohnekabelundsat.levbus.de:8000/live/a.k/a.k/15850.ts</link>
		
		<item>
			<title>GR-: ERT 2</title>
			<link>plugin://plugin.video.f4mTester/?streamtype=TSDOWNLOADER&amp;name=Powered_By_e-Doctor_e-Modder;url=http://tvohnekabelundsat.levbus.de:8000/live/a.k/a.k/15849.ts</link>
		
	



			
			
			
			
			
			
			
			
			
			
			
			
			
			
			
			
			
			
			
			
			
			
			
			
			
			
			
			
			
			
			
			
			
			
			
			
			
			
			
			
			
		<item>
			<title>"[COLOR red][B]SERVER 3[/B][/COLOR]"</title>
			<link>http://......</link>	
						
		<item>
			<title>CY: Rik Sat</title>
			<link>plugin://plugin.video.f4mTester/?streamtype=TSDOWNLOADER&amp;name=Powered_By_e-Doctor_e-Modder;url=http://ipsatpro.com:8000/live/arabian1/arabian1/839.ts</link>
		
		<item>
			<title>GR: 4E</title>
			<link>plugin://plugin.video.f4mTester/?streamtype=TSDOWNLOADER&amp;name=Powered_By_e-Doctor_e-Modder;url=http://ipsatpro.com:8000/live/arabian1/arabian1/841.ts</link>
		
		<item>
			<title>GR: Zougla</title>
			<link>plugin://plugin.video.f4mTester/?streamtype=TSDOWNLOADER&amp;name=Powered_By_e-Doctor_e-Modder;url=http://ipsatpro.com:8000/live/arabian1/arabian1/840.ts</link>
		
		<item>
			<title>GR: SBC</title>
			<link>plugin://plugin.video.f4mTester/?streamtype=TSDOWNLOADER&amp;name=Powered_By_e-Doctor_e-Modder;url=http://ipsatpro.com:8000/live/arabian1/arabian1/870.ts</link>
		
		<item>
			<title>GR: Tv1</title>
			<link>plugin://plugin.video.f4mTester/?streamtype=TSDOWNLOADER&amp;name=Powered_By_e-Doctor_e-Modder;url=http://ipsatpro.com:8000/live/arabian1/arabian1/868.ts</link>
		
		<item>
			<title>GR: Creta tv</title>
			<link>plugin://plugin.video.f4mTester/?streamtype=TSDOWNLOADER&amp;name=Powered_By_e-Doctor_e-Modder;url=http://ipsatpro.com:8000/live/arabian1/arabian1/869.ts</link>
		
		<item>
			<title>CY: Sigma Tv</title>
			<link>plugin://plugin.video.f4mTester/?streamtype=TSDOWNLOADER&amp;name=Powered_By_e-Doctor_e-Modder;url=http://ipsatpro.com:8000/live/arabian1/arabian1/867.ts</link>
		
		<item>
			<title>GR: Tilesport</title>
			<link>plugin://plugin.video.f4mTester/?streamtype=TSDOWNLOADER&amp;name=Powered_By_e-Doctor_e-Modder;url=http://ipsatpro.com:8000/live/arabian1/arabian1/1423.ts</link>
		
		<item>
			<title>GR: National Geo HD</title>
			<link>plugin://plugin.video.f4mTester/?streamtype=TSDOWNLOADER&amp;name=Powered_By_e-Doctor_e-Modder;url=http://ipsatpro.com:8000/live/arabian1/arabian1/1422.ts</link>
		
		<item>
			<title>GR: Messinia</title>
			<link>plugin://plugin.video.f4mTester/?streamtype=TSDOWNLOADER&amp;name=Powered_By_e-Doctor_e-Modder;url=http://ipsatpro.com:8000/live/arabian1/arabian1/846.ts</link>
		
		<item>
			<title>GR: BRT 1</title>
			<link>plugin://plugin.video.f4mTester/?streamtype=TSDOWNLOADER&amp;name=Powered_By_e-Doctor_e-Modder;url=http://ipsatpro.com:8000/live/arabian1/arabian1/878.ts</link>
		
		<item>
			<title>GR: Astra tv</title>
			<link>plugin://plugin.video.f4mTester/?streamtype=TSDOWNLOADER&amp;name=Powered_By_e-Doctor_e-Modder;url=http://ipsatpro.com:8000/live/arabian1/arabian1/877.ts</link>
		
		<item>
			<title>GR: TV100</title>
			<link>plugin://plugin.video.f4mTester/?streamtype=TSDOWNLOADER&amp;name=Powered_By_e-Doctor_e-Modder;url=http://ipsatpro.com:8000/live/arabian1/arabian1/874.ts</link>
		
		<item>
			<title>GR: Nea TV</title>
			<link>plugin://plugin.video.f4mTester/?streamtype=TSDOWNLOADER&amp;name=Powered_By_e-Doctor_e-Modder;url=http://ipsatpro.com:8000/live/arabian1/arabian1/875.ts</link>
		
		<item>
			<title>GR: Kontra Channel</title>
			<link>plugin://plugin.video.f4mTester/?streamtype=TSDOWNLOADER&amp;name=Powered_By_e-Doctor_e-Modder;url=http://ipsatpro.com:8000/live/arabian1/arabian1/876.ts</link>
		
		<item>
			<title>GR: EXTRA</title>
			<link>plugin://plugin.video.f4mTester/?streamtype=TSDOWNLOADER&amp;name=Powered_By_e-Doctor_e-Modder;url=http://ipsatpro.com:8000/live/arabian1/arabian1/873.ts</link>
		
		<item>
			<title>GR: EPT Apxeio</title>
			<link>plugin://plugin.video.f4mTester/?streamtype=TSDOWNLOADER&amp;name=Powered_By_e-Doctor_e-Modder;url=http://ipsatpro.com:8000/live/arabian1/arabian1/861.ts</link>
		
		<item>
			<title>GR: Samiaki</title>
			<link>plugin://plugin.video.f4mTester/?streamtype=TSDOWNLOADER&amp;name=Powered_By_e-Doctor_e-Modder;url=http://ipsatpro.com:8000/live/arabian1/arabian1/860.ts</link>
		
		<item>
			<title>GR: EPT HD</title>
			<link>plugin://plugin.video.f4mTester/?streamtype=TSDOWNLOADER&amp;name=Powered_By_e-Doctor_e-Modder;url=http://ipsatpro.com:8000/live/arabian1/arabian1/872.ts</link>
		
		<item>
			<title>GR: EPT 1</title>
			<link>plugin://plugin.video.f4mTester/?streamtype=TSDOWNLOADER&amp;name=Powered_By_e-Doctor_e-Modder;url=http://ipsatpro.com:8000/live/arabian1/arabian1/871.ts</link>
		
		<item>
			<title>GR: EPT 2</title>
			<link>plugin://plugin.video.f4mTester/?streamtype=TSDOWNLOADER&amp;name=Powered_By_e-Doctor_e-Modder;url=http://ipsatpro.com:8000/live/arabian1/arabian1/866.ts</link>
		
		<item>
			<title>GR: EPT 3</title>
			<link>plugin://plugin.video.f4mTester/?streamtype=TSDOWNLOADER&amp;name=Powered_By_e-Doctor_e-Modder;url=http://ipsatpro.com:8000/live/arabian1/arabian1/865.ts</link>
		
		<item>
			<title>GR: Star</title>
			<link>plugin://plugin.video.f4mTester/?streamtype=TSDOWNLOADER&amp;name=Powered_By_e-Doctor_e-Modder;url=http://ipsatpro.com:8000/live/arabian1/arabian1/848.ts</link>
		
		<item>
			<title>GR: SAKI</title>
			<link>plugin://plugin.video.f4mTester/?streamtype=TSDOWNLOADER&amp;name=Powered_By_e-Doctor_e-Modder;url=http://ipsatpro.com:8000/live/arabian1/arabian1/850.ts</link>
		
		<item>
			<title>GR: Ma tv</title>
			<link>plugin://plugin.video.f4mTester/?streamtype=TSDOWNLOADER&amp;name=Powered_By_e-Doctor_e-Modder;url=http://ipsatpro.com:8000/live/arabian1/arabian1/849.ts</link>
		
		<item>
			<title>GR: Antenna</title>
			<link>plugin://plugin.video.f4mTester/?streamtype=TSDOWNLOADER&amp;name=Powered_By_e-Doctor_e-Modder;url=http://ipsatpro.com:8000/live/arabian1/arabian1/847.ts</link>
		
		<item>
			<title>GR: Kontra TV</title>
			<link>plugin://plugin.video.f4mTester/?streamtype=TSDOWNLOADER&amp;name=Powered_By_e-Doctor_e-Modder;url=http://ipsatpro.com:8000/live/arabian1/arabian1/853.ts</link>
		
		<item>
			<title>GR: Rise</title>
			<link>plugin://plugin.video.f4mTester/?streamtype=TSDOWNLOADER&amp;name=Powered_By_e-Doctor_e-Modder;url=http://ipsatpro.com:8000/live/arabian1/arabian1/864.ts</link>
		
		<item>
			<title>GR: Mega</title>
			<link>plugin://plugin.video.f4mTester/?streamtype=TSDOWNLOADER&amp;name=Powered_By_e-Doctor_e-Modder;url=http://ipsatpro.com:8000/live/arabian1/arabian1/863.ts</link>
		
		<item>
			<title>GR: Mega TV</title>
			<link>plugin://plugin.video.f4mTester/?streamtype=TSDOWNLOADER&amp;name=Powered_By_e-Doctor_e-Modder;url=http://ipsatpro.com:8000/live/arabian1/arabian1/862.ts</link>
		
		<item>
			<title>GR: Alpha</title>
			<link>plugin://plugin.video.f4mTester/?streamtype=TSDOWNLOADER&amp;name=Powered_By_e-Doctor_e-Modder;url=http://ipsatpro.com:8000/live/arabian1/arabian1/855.ts</link>
		
		<item>
			<title>GR: Euronews</title>
			<link>plugin://plugin.video.f4mTester/?streamtype=TSDOWNLOADER&amp;name=Powered_By_e-Doctor_e-Modder;url=http://ipsatpro.com:8000/live/arabian1/arabian1/858.ts</link>
		
		<item>
			<title>GR: Nickelodeon</title>
			<link>plugin://plugin.video.f4mTester/?streamtype=TSDOWNLOADER&amp;name=Powered_By_e-Doctor_e-Modder;url=http://ipsatpro.com:8000/live/arabian1/arabian1/859.ts</link>
		
		<item>
			<title>GR: MAK TV</title>
			<link>plugin://plugin.video.f4mTester/?streamtype=TSDOWNLOADER&amp;name=Powered_By_e-Doctor_e-Modder;url=http://ipsatpro.com:8000/live/arabian1/arabian1/854.ts</link>
		
		<item>
			<title>CY: ANT1</title>
			<link>plugin://plugin.video.f4mTester/?streamtype=TSDOWNLOADER&amp;name=Powered_By_e-Doctor_e-Modder;url=http://ipsatpro.com:8000/live/arabian1/arabian1/856.ts</link>
		
		<item>
			<title>CY: MAD TV</title>
			<link>plugin://plugin.video.f4mTester/?streamtype=TSDOWNLOADER&amp;name=Powered_By_e-Doctor_e-Modder;url=http://ipsatpro.com:8000/live/arabian1/arabian1/857.ts</link>
		
		<item>
			<title>GR: Omega</title>
			<link>plugin://plugin.video.f4mTester/?streamtype=TSDOWNLOADER&amp;name=Powered_By_e-Doctor_e-Modder;url=http://ipsatpro.com:8000/live/arabian1/arabian1/852.ts</link>
		
		<item>
			<title>CY: Ant1 Cyprus</title>
			<link>plugin://plugin.video.f4mTester/?streamtype=TSDOWNLOADER&amp;name=Powered_By_e-Doctor_e-Modder;url=http://ipsatpro.com:8000/live/arabian1/arabian1/851.ts</link>
			
		<item>
			<title>Hot Action HD</title>
			<link>plugin://plugin.video.f4mTester/?streamtype=TSDOWNLOADER&amp;name=Powered_By_e-Doctor_e-Modder;url=http://ipsatpro.com:8000/live/arabian1/arabian1/1427.ts</link>
		
		<item>
			<title>Hot Gold HD</title>
			<link>plugin://plugin.video.f4mTester/?streamtype=TSDOWNLOADER&amp;name=Powered_By_e-Doctor_e-Modder;url=http://ipsatpro.com:8000/live/arabian1/arabian1/1426.ts</link>
			
		<item>
			<title>Let TV</title>
			<link>plugin://plugin.video.f4mTester/?streamtype=TSDOWNLOADER&amp;name=Powered_By_e-Doctor_e-Modder;url=http://ipsatpro.com:8000/live/arabian1/arabian1/836.ts</link>
		
		
		<item>
			<title>GR: Astra Supersport 1</title>
			<link>plugin://plugin.video.f4mTester/?streamtype=TSDOWNLOADER&amp;name=Powered_By_e-Doctor_e-Modder;url=http://ipsatpro.com:8000/live/arabian1/arabian1/845.ts</link>
		
		<item>
			<title>GR: Astra Supersport 2</title>
			<link>plugin://plugin.video.f4mTester/?streamtype=TSDOWNLOADER&amp;name=Powered_By_e-Doctor_e-Modder;url=http://ipsatpro.com:8000/live/arabian1/arabian1/844.ts</link>
		
		<item>
			<title>GR: Astra Supersport 3</title>
			<link>plugin://plugin.video.f4mTester/?streamtype=TSDOWNLOADER&amp;name=Powered_By_e-Doctor_e-Modder;url=http://ipsatpro.com:8000/live/arabian1/arabian1/843.ts</link>
		
		<item>
			<title>GR: Astra Supersport 4</title>
			<link>plugin://plugin.video.f4mTester/?streamtype=TSDOWNLOADER&amp;name=Powered_By_e-Doctor_e-Modder;url=http://ipsatpro.com:8000/live/arabian1/arabian1/842.ts</link>
			
			
			
			
			
			
			
			
			
			
			
			
			
			
			
			
			
			
			
			
			
			
			
			
			
			
			
			
			
			
			
			
			
			
			
			
			
		<item>
			<title>"[COLOR red][B]SERVER 4[/B][/COLOR]"</title>
			<link>http://......</link>	
			
		<item>
			<title>TV 100 (GR)</title>
			<link>plugin://plugin.video.f4mTester/?streamtype=TSDOWNLOADER&amp;name=Powered_By_e-Doctor_e-Modder;url=http://37.187.252.93:8000/live/serdar22/22serdar/9483.ts</link>
		
		<item>
			<title>Star (GR)</title>
			<link>plugin://plugin.video.f4mTester/?streamtype=TSDOWNLOADER&amp;name=Powered_By_e-Doctor_e-Modder;url=http://37.187.252.93:8000/live/serdar22/22serdar/9484.ts</link>
		
		<item>
			<title>Skai (GR)</title>
			<link>plugin://plugin.video.f4mTester/?streamtype=TSDOWNLOADER&amp;name=Powered_By_e-Doctor_e-Modder;url=http://37.187.252.93:8000/live/serdar22/22serdar/9485.ts</link>
		
		<item>
			<title>Sigma (GR)</title>
			<link>plugin://plugin.video.f4mTester/?streamtype=TSDOWNLOADER&amp;name=Powered_By_e-Doctor_e-Modder;url=http://37.187.252.93:8000/live/serdar22/22serdar/9486.ts</link>
		
		<item>
			<title>Omega (GR)</title>
			<link>plugin://plugin.video.f4mTester/?streamtype=TSDOWNLOADER&amp;name=Powered_By_e-Doctor_e-Modder;url=http://37.187.252.93:8000/live/serdar22/22serdar/9487.ts</link>
		
		<item>
			<title>Nickeledeon (GR)</title>
			<link>plugin://plugin.video.f4mTester/?streamtype=TSDOWNLOADER&amp;name=Powered_By_e-Doctor_e-Modder;url=http://37.187.252.93:8000/live/serdar22/22serdar/9488.ts</link>
		
		<item>
			<title>Nea (GR)</title>
			<link>plugin://plugin.video.f4mTester/?streamtype=TSDOWNLOADER&amp;name=Powered_By_e-Doctor_e-Modder;url=http://37.187.252.93:8000/live/serdar22/22serdar/9489.ts</link>
		
		<item>
			<title>Nat Geo (GR)</title>
			<link>plugin://plugin.video.f4mTester/?streamtype=TSDOWNLOADER&amp;name=Powered_By_e-Doctor_e-Modder;url=http://37.187.252.93:8000/live/serdar22/22serdar/9490.ts</link>
		
		<item>
			<title>Mega (GR)</title>
			<link>plugin://plugin.video.f4mTester/?streamtype=TSDOWNLOADER&amp;name=Powered_By_e-Doctor_e-Modder;url=http://37.187.252.93:8000/live/serdar22/22serdar/9491.ts</link>
		
		<item>
			<title>Makadenyo (GR)</title>
			<link>plugin://plugin.video.f4mTester/?streamtype=TSDOWNLOADER&amp;name=Powered_By_e-Doctor_e-Modder;url=http://37.187.252.93:8000/live/serdar22/22serdar/9492.ts</link>
		
		<item>
			<title>Kontra (GR)</title>
			<link>plugin://plugin.video.f4mTester/?streamtype=TSDOWNLOADER&amp;name=Powered_By_e-Doctor_e-Modder;url=http://37.187.252.93:8000/live/serdar22/22serdar/9493.ts</link>
		
		<item>
			<title>Ept 2 (GR)</title>
			<link>plugin://plugin.video.f4mTester/?streamtype=TSDOWNLOADER&amp;name=Powered_By_e-Doctor_e-Modder;url=http://37.187.252.93:8000/live/serdar22/22serdar/9494.ts</link>
		
		<item>
			<title>Ept 1 (GR)</title>
			<link>plugin://plugin.video.f4mTester/?streamtype=TSDOWNLOADER&amp;name=Powered_By_e-Doctor_e-Modder;url=http://37.187.252.93:8000/live/serdar22/22serdar/9495.ts</link>
		
		<item>
			<title>Epsilon (GR)</title>
			<link>plugin://plugin.video.f4mTester/?streamtype=TSDOWNLOADER&amp;name=Powered_By_e-Doctor_e-Modder;url=http://37.187.252.93:8000/live/serdar22/22serdar/9496.ts</link>
		
		<item>
			<title>Boyah (GR)</title>
			<link>plugin://plugin.video.f4mTester/?streamtype=TSDOWNLOADER&amp;name=Powered_By_e-Doctor_e-Modder;url=http://37.187.252.93:8000/live/serdar22/22serdar/9497.ts</link>
		
		<item>
			<title>Astra (GR)</title>
			<link>plugin://plugin.video.f4mTester/?streamtype=TSDOWNLOADER&amp;name=Powered_By_e-Doctor_e-Modder;url=http://37.187.252.93:8000/live/serdar22/22serdar/9498.ts</link>
		
		<item>
			<title>Apt (GR)</title>
			<link>plugin://plugin.video.f4mTester/?streamtype=TSDOWNLOADER&amp;name=Powered_By_e-Doctor_e-Modder;url=http://37.187.252.93:8000/live/serdar22/22serdar/9499.ts</link>
		
		<item>
			<title>Ant 1 (GR)</title>
			<link>plugin://plugin.video.f4mTester/?streamtype=TSDOWNLOADER&amp;name=Powered_By_e-Doctor_e-Modder;url=http://37.187.252.93:8000/live/serdar22/22serdar/9500.ts</link>
		
		<item>
			<title>Alpha (GR)</title>
			<link>plugin://plugin.video.f4mTester/?streamtype=TSDOWNLOADER&amp;name=Powered_By_e-Doctor_e-Modder;url=http://37.187.252.93:8000/live/serdar22/22serdar/9501.ts</link>
		
		<item>
			<title>4E (GR)</title>
			<link>plugin://plugin.video.f4mTester/?streamtype=TSDOWNLOADER&amp;name=Powered_By_e-Doctor_e-Modder;url=http://37.187.252.93:8000/live/serdar22/22serdar/9502.ts</link>
		
	


			
			
			
			
			
			
			
			
			
			
			
		<item>
			<title>"[COLOR red][B]SERVER 5[/B][/COLOR]"</title>
			<link>http://......</link>	
			
		<item>
			<title>GR: Rik Sat</title>
			<link>plugin://plugin.video.f4mTester/?streamtype=TSDOWNLOADER&amp;name=Powered_By_e-Doctor_e-Modder;url=http://ipsatpro.com:8000/live/reg/reg/839.ts</link>
		
		<item>
			<title>GR: 4E</title>
			<link>plugin://plugin.video.f4mTester/?streamtype=TSDOWNLOADER&amp;name=Powered_By_e-Doctor_e-Modder;url=http://ipsatpro.com:8000/live/reg/reg/841.ts</link>
		
		<item>
			<title>GR: Zougla</title>
			<link>plugin://plugin.video.f4mTester/?streamtype=TSDOWNLOADER&amp;name=Powered_By_e-Doctor_e-Modder;url=http://ipsatpro.com:8000/live/reg/reg/840.ts</link>
		
		<item>
			<title>GR: SBC</title>
			<link>plugin://plugin.video.f4mTester/?streamtype=TSDOWNLOADER&amp;name=Powered_By_e-Doctor_e-Modder;url=http://ipsatpro.com:8000/live/reg/reg/870.ts</link>
		
		<item>
			<title>GR: Tv1</title>
			<link>plugin://plugin.video.f4mTester/?streamtype=TSDOWNLOADER&amp;name=Powered_By_e-Doctor_e-Modder;url=http://ipsatpro.com:8000/live/reg/reg/868.ts</link>
		
		<item>
			<title>GR: Creta tv</title>
			<link>plugin://plugin.video.f4mTester/?streamtype=TSDOWNLOADER&amp;name=Powered_By_e-Doctor_e-Modder;url=http://ipsatpro.com:8000/live/reg/reg/869.ts</link>
		
		<item>
			<title>GR: Sigma Tv</title>
			<link>plugin://plugin.video.f4mTester/?streamtype=TSDOWNLOADER&amp;name=Powered_By_e-Doctor_e-Modder;url=http://ipsatpro.com:8000/live/reg/reg/867.ts</link>
		
		<item>
			<title>GR: Tilesport</title>
			<link>plugin://plugin.video.f4mTester/?streamtype=TSDOWNLOADER&amp;name=Powered_By_e-Doctor_e-Modder;url=http://ipsatpro.com:8000/live/reg/reg/1423.ts</link>
		
		<item>
			<title>GR: National Geo HD</title>
			<link>plugin://plugin.video.f4mTester/?streamtype=TSDOWNLOADER&amp;name=Powered_By_e-Doctor_e-Modder;url=http://ipsatpro.com:8000/live/reg/reg/1422.ts</link>
		
		<item>
			<title>GR: Messinia</title>
			<link>plugin://plugin.video.f4mTester/?streamtype=TSDOWNLOADER&amp;name=Powered_By_e-Doctor_e-Modder;url=http://ipsatpro.com:8000/live/reg/reg/846.ts</link>
		
		<item>
			<title>GR: BRT 1</title>
			<link>plugin://plugin.video.f4mTester/?streamtype=TSDOWNLOADER&amp;name=Powered_By_e-Doctor_e-Modder;url=http://ipsatpro.com:8000/live/reg/reg/878.ts</link>
		
		<item>
			<title>GR: Astra tv</title>
			<link>plugin://plugin.video.f4mTester/?streamtype=TSDOWNLOADER&amp;name=Powered_By_e-Doctor_e-Modder;url=http://ipsatpro.com:8000/live/reg/reg/877.ts</link>
		
		<item>
			<title>GR: TV100</title>
			<link>plugin://plugin.video.f4mTester/?streamtype=TSDOWNLOADER&amp;name=Powered_By_e-Doctor_e-Modder;url=http://ipsatpro.com:8000/live/reg/reg/874.ts</link>
		
		<item>
			<title>GR: Nea TV</title>
			<link>plugin://plugin.video.f4mTester/?streamtype=TSDOWNLOADER&amp;name=Powered_By_e-Doctor_e-Modder;url=http://ipsatpro.com:8000/live/reg/reg/875.ts</link>
		
		<item>
			<title>GR: Kontra Channel</title>
			<link>plugin://plugin.video.f4mTester/?streamtype=TSDOWNLOADER&amp;name=Powered_By_e-Doctor_e-Modder;url=http://ipsatpro.com:8000/live/reg/reg/876.ts</link>
		
		<item>
			<title>GR: EXTRA</title>
			<link>plugin://plugin.video.f4mTester/?streamtype=TSDOWNLOADER&amp;name=Powered_By_e-Doctor_e-Modder;url=http://ipsatpro.com:8000/live/reg/reg/873.ts</link>
		
		<item>
			<title>GR: EPT Apxeio</title>
			<link>plugin://plugin.video.f4mTester/?streamtype=TSDOWNLOADER&amp;name=Powered_By_e-Doctor_e-Modder;url=http://ipsatpro.com:8000/live/reg/reg/861.ts</link>
		
		<item>
			<title>GR: Samiaki</title>
			<link>plugin://plugin.video.f4mTester/?streamtype=TSDOWNLOADER&amp;name=Powered_By_e-Doctor_e-Modder;url=http://ipsatpro.com:8000/live/reg/reg/860.ts</link>
		
		<item>
			<title>GR: EPT HD</title>
			<link>plugin://plugin.video.f4mTester/?streamtype=TSDOWNLOADER&amp;name=Powered_By_e-Doctor_e-Modder;url=http://ipsatpro.com:8000/live/reg/reg/872.ts</link>
		
		<item>
			<title>GR: EPT 1</title>
			<link>plugin://plugin.video.f4mTester/?streamtype=TSDOWNLOADER&amp;name=Powered_By_e-Doctor_e-Modder;url=http://ipsatpro.com:8000/live/reg/reg/871.ts</link>
		
		<item>
			<title>GR: EPT 2</title>
			<link>plugin://plugin.video.f4mTester/?streamtype=TSDOWNLOADER&amp;name=Powered_By_e-Doctor_e-Modder;url=http://ipsatpro.com:8000/live/reg/reg/866.ts</link>
		
		<item>
			<title>GR: EPT 3</title>
			<link>plugin://plugin.video.f4mTester/?streamtype=TSDOWNLOADER&amp;name=Powered_By_e-Doctor_e-Modder;url=http://ipsatpro.com:8000/live/reg/reg/865.ts</link>
		
		<item>
			<title>GR: Star</title>
			<link>plugin://plugin.video.f4mTester/?streamtype=TSDOWNLOADER&amp;name=Powered_By_e-Doctor_e-Modder;url=http://ipsatpro.com:8000/live/reg/reg/848.ts</link>
		
		<item>
			<title>GR: SAKI</title>
			<link>plugin://plugin.video.f4mTester/?streamtype=TSDOWNLOADER&amp;name=Powered_By_e-Doctor_e-Modder;url=http://ipsatpro.com:8000/live/reg/reg/850.ts</link>
		
		<item>
			<title>GR: Ma tv</title>
			<link>plugin://plugin.video.f4mTester/?streamtype=TSDOWNLOADER&amp;name=Powered_By_e-Doctor_e-Modder;url=http://ipsatpro.com:8000/live/reg/reg/849.ts</link>
		
		<item>
			<title>GR: Antenna</title>
			<link>plugin://plugin.video.f4mTester/?streamtype=TSDOWNLOADER&amp;name=Powered_By_e-Doctor_e-Modder;url=http://ipsatpro.com:8000/live/reg/reg/847.ts</link>
		
		<item>
			<title>GR: Kontra TV</title>
			<link>plugin://plugin.video.f4mTester/?streamtype=TSDOWNLOADER&amp;name=Powered_By_e-Doctor_e-Modder;url=http://ipsatpro.com:8000/live/reg/reg/853.ts</link>
		
		<item>
			<title>GR: MTV Music</title>
			<link>plugin://plugin.video.f4mTester/?streamtype=TSDOWNLOADER&amp;name=Powered_By_e-Doctor_e-Modder;url=http://ipsatpro.com:8000/live/reg/reg/864.ts</link>
		
		<item>
			<title>GR: Mega</title>
			<link>plugin://plugin.video.f4mTester/?streamtype=TSDOWNLOADER&amp;name=Powered_By_e-Doctor_e-Modder;url=http://ipsatpro.com:8000/live/reg/reg/863.ts</link>
		
		<item>
			<title>GR: Mega TV</title>
			<link>plugin://plugin.video.f4mTester/?streamtype=TSDOWNLOADER&amp;name=Powered_By_e-Doctor_e-Modder;url=http://ipsatpro.com:8000/live/reg/reg/862.ts</link>
		
		<item>
			<title>GR: Alpha</title>
			<link>plugin://plugin.video.f4mTester/?streamtype=TSDOWNLOADER&amp;name=Powered_By_e-Doctor_e-Modder;url=http://ipsatpro.com:8000/live/reg/reg/855.ts</link>
		
		<item>
			<title>GR: Euronews</title>
			<link>plugin://plugin.video.f4mTester/?streamtype=TSDOWNLOADER&amp;name=Powered_By_e-Doctor_e-Modder;url=http://ipsatpro.com:8000/live/reg/reg/858.ts</link>
		
		<item>
			<title>GR: Nickelodeon</title>
			<link>plugin://plugin.video.f4mTester/?streamtype=TSDOWNLOADER&amp;name=Powered_By_e-Doctor_e-Modder;url=http://ipsatpro.com:8000/live/reg/reg/859.ts</link>
		
		<item>
			<title>GR: MAK TV</title>
			<link>plugin://plugin.video.f4mTester/?streamtype=TSDOWNLOADER&amp;name=Powered_By_e-Doctor_e-Modder;url=http://ipsatpro.com:8000/live/reg/reg/854.ts</link>
		
		<item>
			<title>GR: ANT1</title>
			<link>plugin://plugin.video.f4mTester/?streamtype=TSDOWNLOADER&amp;name=Powered_By_e-Doctor_e-Modder;url=http://ipsatpro.com:8000/live/reg/reg/856.ts</link>
		
		<item>
			<title>GR: MAD TV</title>
			<link>plugin://plugin.video.f4mTester/?streamtype=TSDOWNLOADER&amp;name=Powered_By_e-Doctor_e-Modder;url=http://ipsatpro.com:8000/live/reg/reg/857.ts</link>
		
		<item>
			<title>GR: Omega</title>
			<link>plugin://plugin.video.f4mTester/?streamtype=TSDOWNLOADER&amp;name=Powered_By_e-Doctor_e-Modder;url=http://ipsatpro.com:8000/live/reg/reg/852.ts</link>
		
		<item>
			<title>GR: Ant1 Cyprus</title>
			<link>plugin://plugin.video.f4mTester/?streamtype=TSDOWNLOADER&amp;name=Powered_By_e-Doctor_e-Modder;url=http://ipsatpro.com:8000/live/reg/reg/851.ts</link>
		
	

			
			
